[
    {
     "studentId": "u4u1",
     "email": "analiaduarteg@gmail.com",
     "fname": "Analía",
     "lname": "Duarte Gálvez",
     "phone": "595991712840",
     "type": "Estudiante",
     "rsvp": "Registrado",
     "source": "Facebook",
     "sourcenote": "Campaña 1"
    },
    {
     "studentId": "u4u2",
     "email": "anamariabolftalavera@gmail.com",
     "fname": "Anamaria",
     "lname": "Bolf",
     "phone": "595981739944",
     "rsvp": "Registrado",
     "source": "Instagram",
     "sourcenote": "Campaña 1"
    },
    {
     "studentId": "u4u3",
     "email": "belunlole92@gmail.com",
     "fname": "??????",
     "lname": "???????",
     "phone": "595992966232",
     "type": "Estudiante",
     "rsvp": "Registrado",
     "source": "WebSite Visit",
     "sourcenote": "direct"
    },
    {
     "studentId": "u4u4",
     "email": "Claumongelos@gmail.com",
     "fname": "Claudia",
     "lname": "Mongelos",
     "phone": "595991555555",
     "type": "Padre",
     "rsvp": "Registrado",
     "source": "Facebook",
     "sourcenote": "Campaña 1"
    },
    {
     "studentId": "u4u5",
     "email": "ddanhalujan@gmail.com",
     "fname": "Danha",
     "lname": "Diaz",
     "phone": "595991192635",
     "type": "Estudiante",
     "rsvp": "Registrado",
     "source": "Instagram",
     "sourcenote": "Campaña 1"
    },
    {
     "studentId": "u4u6",
     "email": "doctora07@gmail.com",
     "fname": "María Rosa Araujo",
     "lname": "G",
     "phone": "595971177040",
     "type": "Padre",
     "rsvp": "Registrado",
     "source": "WebSite Visit",
     "sourcenote": "direct"
    },
    {
     "studentId": "u4u7",
     "email": "fernandezvictoriamagali94@gmail.com",
     "fname": "Victoria Fernández",
     "lname": "Sosa",
     "phone": "595984143219",
     "type": "Estudiante",
     "rsvp": "Registrado",
     "source": "Facebook",
     "sourcenote": "Campaña 1"
    },
    {
     "studentId": "u4u8",
     "email": "gabyafleitas@gmail.com",
     "fname": "Gabriela",
     "lname": "Fleitas",
     "phone": "595975153335",
     "type": "Estudiante",
     "rsvp": "Registrado",
     "source": "Instagram",
     "sourcenote": "Campaña 1"
    },
    {
     "studentId": "u4u9",
     "email": "gacasaccia@hotmail.com",
     "fname": "Sonnia carolina",
     "lname": "Spezzini",
     "phone": "595982898228",
     "type": "Padre",
     "rsvp": "Registrado",
     "source": "WebSite Visit",
     "sourcenote": "direct"
    },
    {
     "studentId": "u4u10",
     "email": "giovivannaingolotti@hotmail.com",
     "fname": "Vicky",
     "lname": "Ingolotti",
     "phone": "595982873524",
     "type": "Padre",
     "rsvp": "Registrado",
     "source": "Facebook",
     "sourcenote": "Campaña 1"
    },
    {
     "studentId": "u4u11",
     "email": "gloriayum04@gmail.com",
     "fname": "Maria Gloria",
     "lname": "Cañiza",
     "phone": "595992889415",
     "type": "Padre",
     "rsvp": "Registrado",
     "source": "Instagram",
     "sourcenote": "Campaña 1"
    },
    {
     "studentId": "u4u12",
     "email": "guteconomistpy@gmail.com",
     "fname": "Jonathan",
     "lname": "Garcia",
     "phone": "595991208662",
     "type": "Estudiante",
     "rsvp": "Registrado",
     "source": "WebSite Visit",
     "sourcenote": "direct"
    },
    {
     "studentId": "u4u13",
     "email": "ilseroa07@gmail.com",
     "fname": "Ilse Roa Beauty",
     "lname": "Influecer",
     "phone": "595981693873",
     "type": "Padre",
     "rsvp": "Registrado",
     "source": "Facebook",
     "sourcenote": "Campaña 1"
    },
    {
     "studentId": "u4u14",
     "email": "ivanrojasraggio@gmail.com",
     "fname": "Iván",
     "lname": "Gabriel",
     "phone": "595991326217",
     "type": "Estudiante",
     "rsvp": "Registrado",
     "source": "Instagram",
     "sourcenote": "Campaña 1"
    },
    {
     "studentId": "u4u15",
     "email": "jadiyi350@gmail.com",
     "fname": "Jadistier",
     "lname": "González",
     "phone": "982161758",
     "type": "Estudiante",
     "rsvp": "Registrado",
     "source": "WebSite Visit",
     "sourcenote": "direct"
    },
    {
     "studentId": "u4u16",
     "email": "loren.vise22@gmail.com",
     "fname": "Marta",
     "lname": "ortiz",
     "phone": "595985541710",
     "type": "Padre",
     "rsvp": "Registrado",
     "source": "Facebook",
     "sourcenote": "Campaña 1"
    },
    {
     "studentId": "u4u17",
     "email": "lore_fer66@hotmail.com",
     "fname": "Lorena",
     "lname": "Fernandez",
     "phone": "595981966830",
     "type": "Padre",
     "rsvp": "Registrado",
     "source": "Instagram",
     "sourcenote": "Campaña 1"
    },
    {
     "studentId": "u4u18",
     "email": "lucasmanuel1705@gmail.com",
     "fname": "Lucas",
     "lname": "Manuel",
     "phone": "595984150562",
     "type": "Estudiante",
     "rsvp": "Registrado",
     "source": "WebSite Visit",
     "sourcenote": "direct"
    },
    {
     "studentId": "u4u19",
     "email": "lucasnatanaelflorentin@gmail.com",
     "fname": "Florentin",
     "lname": "Lucas",
     "phone": "595981743511",
     "type": "Estudiante",
     "rsvp": "Registrado",
     "source": "Facebook",
     "sourcenote": "Campaña 1"
    },
    {
     "studentId": "u4u20",
     "email": "mariadelpilarcantero@gmail.com",
     "fname": "Marita",
     "lname": "Cantero",
     "type": "Padre",
     "rsvp": "Registrado",
     "source": "Instagram",
     "sourcenote": "Campaña 1"
    },
    {
     "studentId": "u4u21",
     "email": "marianabrescia2004@hotmail.com",
     "fname": "Mariana",
     "lname": "Brescia",
     "phone": "595981181896",
     "type": "Padre",
     "rsvp": "Registrado",
     "source": "WebSite Visit",
     "sourcenote": "direct"
    },
    {
     "studentId": "u4u22",
     "email": "miryambalotta19@gmail.com",
     "fname": "Miryam",
     "lname": "Balotta",
     "phone": "595992670084",
     "type": "Padre",
     "rsvp": "Registrado",
     "source": "Facebook",
     "sourcenote": "Campaña 1"
    },
    {
     "studentId": "u4u23",
     "email": "monsecanteroaguero@gmail.com",
     "fname": "Monse",
     "lname": "Cantero",
     "phone": "595971166250",
     "type": "Estudiante",
     "rsvp": "Registrado",
     "source": "Instagram",
     "sourcenote": "Campaña 1"
    },
    {
     "studentId": "u4u24",
     "email": "olgagiem@hotmail.com",
     "fname": "Maria Olga",
     "lname": "Gimenez",
     "phone": "595981258802",
     "type": "Padre",
     "rsvp": "Registrado",
     "source": "WebSite Visit",
     "sourcenote": "direct"
    },
    {
     "studentId": "u4u25",
     "email": "pameoctubre17@gmail.com",
     "fname": "Pamela",
     "lname": "Villalba Santa Cruz",
     "phone": "595962117473",
     "type": "Padre",
     "rsvp": "Registrado",
     "source": "Facebook",
     "sourcenote": "Campaña 1"
    },
    {
     "studentId": "u4u26",
     "email": "paolainsfran80@gmail.com",
     "fname": "Paola Insfrán",
     "lname": "Alborno",
     "phone": "595981432804",
     "type": "Padre",
     "rsvp": "Registrado",
     "source": "Instagram",
     "sourcenote": "Campaña 1"
    },
    {
     "studentId": "u4u27",
     "email": "rdimartino@webxprs.com",
     "fname": "Rosa Elena",
     "lname": "Di Martino",
     "phone": "595986100750",
     "type": "Padre",
     "rsvp": "Registrado",
     "source": "WebSite Visit",
     "sourcenote": "direct"
    },
    {
     "studentId": "u4u28",
     "email": "reynaldofl@hotmail.com",
     "fname": "Reinaldo Rafael",
     "lname": "Ferreira López",
     "phone": "595971696003",
     "type": "Padre",
     "rsvp": "Registrado",
     "source": "Facebook",
     "sourcenote": "Campaña 1"
    },
    {
     "studentId": "u4u29",
     "email": "rodasjulieta077@gmail.com",
     "fname": "Julieta",
     "lname": "Rodas",
     "phone": "986667726",
     "type": "Estudiante",
     "rsvp": "Registrado",
     "source": "Instagram",
     "sourcenote": "Campaña 1"
    },
    {
     "studentId": "u4u30",
     "email": "saharycubilla@icloud.com",
     "fname": "•Sahy",
     "lname": "Cubilla",
     "phone": "595976317804",
     "type": "Estudiante",
     "rsvp": "Registrado",
     "source": "WebSite Visit",
     "sourcenote": "direct"
    },
    {
     "studentId": "u4u31",
     "email": "samuel.sanchez741@gmail.com",
     "fname": "Samuel",
     "lname": "Sanchez",
     "phone": "595981432278",
     "type": "Estudiante",
     "rsvp": "Registrado",
     "source": "Facebook",
     "sourcenote": "Campaña 1"
    },
    {
     "studentId": "u4u32",
     "email": "stefy2307@hotmail.com",
     "fname": "Stefany",
     "lname": "Santander",
     "phone": "595981604321",
     "type": "Padre",
     "rsvp": "Registrado",
     "source": "Instagram",
     "sourcenote": "Campaña 1"
    },
    {
     "studentId": "u4u33",
     "email": "Tamarawagnerb9@gmail.com",
     "fname": "Tamara",
     "lname": "Wagner",
     "phone": "595971708776",
     "type": "Estudiante",
     "rsvp": "Registrado",
     "source": "WebSite Visit",
     "sourcenote": "direct"
    },
    {
     "studentId": "u4u34",
     "email": "Tatyflo07@gmail.com",
     "fname": "Tatyana",
     "lname": "Florentin",
     "phone": "981823170",
     "type": "Estudiante",
     "rsvp": "Registrado",
     "source": "Facebook",
     "sourcenote": "Campaña 1"
    },
    {
     "studentId": "u4u35",
     "email": "uniamericanamili@gmail.com",
     "fname": "????????",
     "lname": "??????",
     "phone": "982987876",
     "type": "Estudiante",
     "rsvp": "Registrado",
     "source": "Instagram",
     "sourcenote": "Campaña 1"
    }
   ]